code_qa/__init__.py
code_qa/cli.py
code_qa/logger.py
code_qa/utils.py
code_qa-0.3.1.dist-info/entry_points.txt
code_qa-0.3.1.dist-info/LICENSE
code_qa-0.3.1.dist-info/WHEEL
code_qa-0.3.1.dist-info/METADATA
code_qa-0.3.1.dist-info/RECORD
