Metadata-Version: 2.1
Name: code-qa
Version: 0.3.1
Summary: CodeQA: Unleash the power of AI in your codebase. Ask questions & get insights from your document.
Author: Steven Mi
Author-email: steven.mi@getyourguide.com
Requires-Python: >=3.8.1,<4.0
Classifier: Programming Language :: Python :: 3
Classifier: Programming Language :: Python :: 3.9
Classifier: Programming Language :: Python :: 3.10
Classifier: Programming Language :: Python :: 3.11
Requires-Dist: chromadb (>=0.3.25,<0.4.0)
Requires-Dist: fire (>=0.5.0,<0.6.0)
Requires-Dist: langchain (>=0.0.187,<0.0.188)
Requires-Dist: openai (>=0.27.7,<0.28.0)
Requires-Dist: pathspec (>=0.11.1,<0.12.0)
Requires-Dist: tiktoken (>=0.4.0,<0.5.0)
